[
	{
		"name" : "arbitrary_hash_string",
		"url" : "http://www.mysite.com",
		"status_code" : 200,
		"redirects" : [],
		"page_links" : ["could_be_an_id", "could be anything", "a6f28cn316sa"]
	},
	{
		"name" : "could_be_an_id",
		"url" : "/aboutus/",
		"status_code" : 200,
		"redirects" : ["http://www.mysite.com/about/"],
		"page_links" : ["arbitrary_hash_string"]
	},
	{
		"name" : "could be anything",
		"url" : "/login/",
		"status_code" : 200,
		"redirects" : [],
		"page_links" : []
	},
	{
		"name" : "a6f28cn316sa",
		"url" : "/products/",
		"status_code" : 404,
		"redirects" : [],
		"page_links" : []
	}
]